[
  {
    "nanoid": "FXQtm2S6eQXf1s",
    "name": "B+ TV",
    "stream_urls": [
      "https://tv.btnrwanda.com:3432/live/bpluslive.m3u8"
    ],
    "youtube_urls": [],
    "languages": [
      "eng",
      "kin"
    ],
    "country": "rw",
    "isGeoBlocked": false
  },
  {
    "nanoid": "hRgd0Ypxitc2Uq",
    "name": "BTN TV",
    "stream_urls": [
      "https://tv.btnrwanda.com:3086/live/btnlive.m3u8"
    ],
    "youtube_urls": [],
    "languages": [
      "kin"
    ],
    "country": "rw",
    "isGeoBlocked": false
  }
]